teer/__about__.py
teer/__init__.py
teer/http.py
teer/py.typed
teer/types.py
teer/resources/__init__.py
teer/resources/base.py
teer/resources/billing.py
teer/resources/ingest.py
teer-0.1.7.data/data/teer/py.typed
teer-0.1.7.dist-info/METADATA
teer-0.1.7.dist-info/WHEEL
teer-0.1.7.dist-info/licenses/LICENSE.txt
teer-0.1.7.dist-info/RECORD
