Metadata-Version: 2.4
Name: teer
Version: 0.1.7
Summary: Teer Python SDK
Project-URL: Documentation, https://github.com/teerai/teer-python#readme
Project-URL: Issues, https://github.com/teerai/teer-python/issues
Project-URL: Source, https://github.com/teerai/teer-python
Author-email: Shane Rogers <shane@teer.ai>
License-Expression: MIT
License-File: LICENSE.txt
Keywords: analytics,llm,tracking
Classifier: Development Status :: 4 - Beta
Classifier: Programming Language :: Python
Classifier: Programming Language :: Python :: 3.8
Classifier: Programming Language :: Python :: 3.9
Classifier: Programming Language :: Python :: 3.10
Classifier: Programming Language :: Python :: 3.11
Classifier: Programming Language :: Python :: 3.12
Classifier: Programming Language :: Python :: Implementation :: CPython
Classifier: Programming Language :: Python :: Implementation :: PyPy
Classifier: Typing :: Typed
Requires-Python: >=3.8
Requires-Dist: requests>=2.25.0
